toweb/__init__.py
toweb/server.py
toweb/viewer.html
toweb/static/bundle.js
toweb/static/logo.png
toweb-0.0.7.dist-info/METADATA
toweb-0.0.7.dist-info/WHEEL
toweb-0.0.7.dist-info/top_level.txt
toweb-0.0.7.dist-info/RECORD
